empyrical/__init__.py
empyrical/_version.py
empyrical/deprecate.py
empyrical/perf_attrib.py
empyrical/periods.py
empyrical/stats.py
empyrical/utils.py
empyrical_reloaded-0.5.11.dist-info/LICENSE
empyrical_reloaded-0.5.11.dist-info/METADATA
empyrical_reloaded-0.5.11.dist-info/WHEEL
empyrical_reloaded-0.5.11.dist-info/top_level.txt
empyrical_reloaded-0.5.11.dist-info/RECORD
