Metadata-Version: 2.1
Name: empyrical-reloaded
Version: 0.5.11
Summary: empyrical computes performance and risk statistics commonly used in quantitative finance
Author: Quantopian Inc
Author-email: pm@ml4trading.io
Maintainer: Stefan Jansen
Maintainer-email: pm@ml4trading.io
License:                                  Apache License
Project-URL: homepage, https://ml4trading.io
Project-URL: documentation, https://empyrical.ml4trading.io
Project-URL: repository, https://github.com/stefan-jansen/empyrical-reloaded
Classifier: Development Status :: 4 - Beta
Classifier: Programming Language :: Python
Classifier: Programming Language :: Python :: 3.9
Classifier: Programming Language :: Python :: 3.10
Classifier: Programming Language :: Python :: 3.11
Classifier: Programming Language :: Python :: 3.12
Classifier: License :: OSI Approved :: Apache Software License
Classifier: Intended Audience :: Science/Research
Classifier: Topic :: Scientific/Engineering
Classifier: Topic :: Scientific/Engineering :: Mathematics
Classifier: Operating System :: OS Independent
Requires-Python: >=3.9
License-File: LICENSE
Requires-Dist: numpy>=1.23.5; python_version < "3.12"
Requires-Dist: numpy>=1.26.0; python_version >= "3.12"
Requires-Dist: pandas>=1.3.0; python_version < "3.12"
Requires-Dist: pandas>=2.2.2; python_version >= "3.12"
Requires-Dist: bottleneck>=1.3.0
Requires-Dist: pandas>=1.3.0
Requires-Dist: scipy>=0.15.1
Requires-Dist: peewee<3.17.4
Provides-Extra: test
Requires-Dist: tox>=2.3.1; extra == "test"
Requires-Dist: pytest>=6.2.3; extra == "test"
Requires-Dist: pytest-cov>=2.11.1; extra == "test"
Requires-Dist: flake8>=3.9.1; extra == "test"
Requires-Dist: black; extra == "test"
Provides-Extra: dev
Requires-Dist: flake8>=3.9.1; extra == "dev"
Requires-Dist: black; extra == "dev"
Requires-Dist: pre-commit>=2.12.1; extra == "dev"
Provides-Extra: doc
Requires-Dist: Cython; extra == "doc"
Requires-Dist: Sphinx>=1.3.2; extra == "doc"
Requires-Dist: numpydoc>=0.5.0; extra == "doc"
Requires-Dist: sphinx-autobuild>=0.6.0; extra == "doc"
Requires-Dist: pydata-sphinx-theme; extra == "doc"
Requires-Dist: sphinx-markdown-tables; extra == "doc"
Requires-Dist: sphinx_copybutton; extra == "doc"
Requires-Dist: nbsphinx; extra == "doc"
Requires-Dist: m2r2; extra == "doc"
Provides-Extra: yfinance
Requires-Dist: yfinance>=0.1.63; extra == "yfinance"
Provides-Extra: datareader
Requires-Dist: pandas-datareader>=0.4; extra == "datareader"
